pre_commit_license_headers/__init__.py
pre_commit_license_headers/check_license_headers.py
pre_commit_license_headers/file_types.py
pre_commit_license_headers-0.1.0.dist-info/entry_points.txt
pre_commit_license_headers-0.1.0.dist-info/LICENSE
pre_commit_license_headers-0.1.0.dist-info/WHEEL
pre_commit_license_headers-0.1.0.dist-info/METADATA
pre_commit_license_headers-0.1.0.dist-info/RECORD
