Metadata-Version: 2.1
Name: pre-commit-license-headers
Version: 0.1.0
Summary: A pre-commit hook to check source code license headers
Home-page: https://github.com/johannsdg/pre-commit-license-headers
License: BSD-3-Clause
Keywords: pre-commit,license,copyright,utility,python
Author: Jeffrey James
Author-email: lobotmcj@gmail.com
Requires-Python: >=3.6.2,<4.0.0
Classifier: License :: OSI Approved :: BSD License
Classifier: Programming Language :: Python :: 3
Classifier: Programming Language :: Python :: 3.7
Classifier: Programming Language :: Python :: 3.8
Classifier: Programming Language :: Python :: 3.9
Requires-Dist: identify (>=2.2.13,<3.0.0)
Project-URL: Repository, https://github.com/johannsdg/pre-commit-license-headers
